flask_sslify_bp.py
Flask_SSLify_bp-0.1.6.dist-info/DESCRIPTION.rst
Flask_SSLify_bp-0.1.6.dist-info/LICENSE.txt
Flask_SSLify_bp-0.1.6.dist-info/METADATA
Flask_SSLify_bp-0.1.6.dist-info/RECORD
Flask_SSLify_bp-0.1.6.dist-info/WHEEL
Flask_SSLify_bp-0.1.6.dist-info/metadata.json
Flask_SSLify_bp-0.1.6.dist-info/top_level.txt
