Metadata-Version: 2.0
Name: Flask-SSLify-bp
Version: 0.1.6
Summary: Force SSL on your Flask app.
Home-page: https://github.com/traherom/flask-sslify
Author: Kenneth Reitz
Author-email: ryan@moreharts.com
License: BSD
Platform: any
Classifier: Environment :: Web Environment
Classifier: Intended Audience :: Developers
Classifier: License :: OSI Approved :: BSD License
Classifier: Operating System :: OS Independent
Classifier: Programming Language :: Python
Classifier: Programming Language :: Python :: 3
Classifier: Topic :: Internet :: WWW/HTTP :: Dynamic Content
Classifier: Topic :: Software Development :: Libraries :: Python Modules
Requires-Dist: Flask
